{
  "dialogueGraphs": [
    {
      "id": "DG_STAGING_INTERCONNECTION_BAY",
      "sceneId": "SCN-060",
      "startNodeId": "N_START",
      "nodes": [
        {
          "id": "N_START",
          "type": "npc_line",
          "speakerId": "NARRATOR",
          "text": "Interconnection Bay Staging: a bright, over-labeled room pretending it\u2019s temporary. (pause)\nThe AMR reader loop hums with the confidence of something never cross-examined. (pause)\nA clipboard station sits under a sign: PLEASE PRINT, as if handwriting is the primary hazard.",
          "next": "N_SUP_HOLD"
        },
        {
          "id": "N_SUP_HOLD",
          "type": "npc_line",
          "speakerId": "BAY_SUPERVISOR",
          "text": "Hold up. (pause) Hands off. (pause) I need the work envelope. (pause) Three items. (pause) Put 'em right here. (pause) If it\u0019s not in the file, (pause) I can\u0019t back it.",
          "next": "N_SUP_PREREQ"
        },
        {
          "id": "N_SUP_PREREQ",
          "type": "npc_line",
          "speakerId": "BAY_SUPERVISOR",
          "text": "Okay. IWO\u0019s on the sheet. (pause) Slot token\u0019s here. (pause) AMR\u0019s issued. (pause) Fine. We stage. (pause) Call it staging and move.",
          "next": "N_HUB"
        },
        {
          "id": "N_HUB",
          "type": "player_choice",
          "speakerId": "PLAYER",
          "choices": [
            {
              "id": "C_ASK_MISSING",
              "text": "ask: What\u2019s missing?",
              "next": "N_SUP_MISSING"
            },
            {
              "id": "C_ASK_BALANCED",
              "text": "ask: Define \u201cbalanced.\u201d",
              "next": "N_SUP_BALANCED"
            },
            {
              "id": "C_ASK_RUNNING",
              "text": "ask: It looks like it\u2019s already running.",
              "next": "N_SUP_RUNNING"
            },
            {
              "id": "C_ASK_SHOW_AMR",
              "text": "ask: Show me where you want the AMR.",
              "next": "N_SUP_SHOW_AMR"
            },
            {
              "id": "C_SHOW_PAPERWORK",
              "text": "show: Show the IWO, token, and AMR issuance record.",
              "next": "N_SUP_PAPERWORK"
            },
            {
              "id": "C_USE_WORK",
              "text": "use: Let me work.",
              "next": "N_SUP_WORK"
            },
            {
              "id": "C_PERSUADE_AUTH",
              "text": "persuade: You have what you need. Log it and clear me.",
              "checks": [
                {
                  "type": "faction_member",
                  "faction": "OLEA"
                }
              ],
              "onPassNext": "N_SUP_PERSUADE_PASS",
              "onFailNext": "N_SUP_PERSUADE_FAIL"
            },
            {
              "id": "C_LEAVE_END",
              "text": "leave: Back.",
              "next": "N_END_BACK"
            }
          ]
        },
        {
          "id": "N_SUP_MISSING",
          "type": "npc_line",
          "speakerId": "BAY_SUPERVISOR",
          "text": "Nothing\u2019s missing. (pause)\nIt\u2019s just not in order on the page. (pause)\nAMR into the reader loop. (pause)\nSeat the dummy mass. (pause)\nThen set the test load panel. (pause)\nThen initial at the clipboard station. (pause)\nI need a clean line to point at (pause)\nwhen review hits.",
          "next": "N_REDIRECT_HUB"
        },
        {
          "id": "N_SUP_BALANCED",
          "type": "npc_line",
          "speakerId": "BAY_SUPERVISOR",
          "text": "Balanced means the test load stays in tolerance (pause) through the phase-lock window. (pause) Maintenance window, yeah. (pause) We just watch it hold. (pause) And don\u0019t throw \u001ctrigger\u001d around\u0014 (pause) depositions love that word.",
          "next": "N_REDIRECT_HUB"
        },
        {
          "id": "N_SUP_RUNNING",
          "type": "npc_line",
          "speakerId": "BAY_SUPERVISOR",
          "text": "Yeah, it runs. (pause)\nJust don\u0019t say \u001calready.\u001d (pause)\nThat word makes people start asking why. (pause)\nIt was supposed to be stopped. (pause)\nYou\u0019re here to correct routing\u0014reverse\u0014 (pause)\nwith authorization.",
          "next": "N_REDIRECT_HUB"
        },
        {
          "id": "N_SUP_SHOW_AMR",
          "type": "npc_line",
          "speakerId": "BAY_SUPERVISOR",
          "text": "Brass oval at waist height. (pause) Reader loop. (pause)\nClip the AMR. (pause) Arrow points toward the hinge. (pause)\nYeah, it reads either way. (pause)\nUpside down makes the log look like guessing. (pause)\nAnd we've had enough. (pause)\n\"unexpected reflective behavior\".",
          "next": "N_REDIRECT_HUB"
        },
        {
          "id": "N_SUP_PAPERWORK",
          "type": "npc_line",
          "speakerId": "BAY_SUPERVISOR",
          "text": "I\u0019m not signing off. (pause) I\u0019m logging what\u0019s valid\u0014and the order. (pause) If it\u0019s going to survive review, (pause) it needs to read like wallpaper.",
          "next": "N_REDIRECT_HUB"
        },
        {
          "id": "N_SUP_WORK",
          "type": "npc_line",
          "speakerId": "BAY_SUPERVISOR",
          "text": "Work. Sure. (pause) Stay in sequence. (pause)\nWatch what you say at the equipment. (pause)\nThe machine won\u0019t care. (pause)\nThe record will.",
          "next": "N_REDIRECT_HUB"
        },
        {
          "id": "N_SUP_PERSUADE_PASS",
          "type": "npc_line",
          "speakerId": "BAY_SUPERVISOR",
          "text": "You're OLEA. (pause)\nSo yeah. You want me to clear you. (pause)\nI can confirm what's on the sheet. (pause)\nAMR recognized. Token present. IWO valid. (pause)\nYou finish the checklist. (pause)\nLoad hits staging tolerance. (pause)\nI confirm that. (pause)\nThat opens the next door. (pause)\nAnd I don't end up in a hearing.",
          "next": "N_REDIRECT_HUB"
        },
        {
          "id": "N_SUP_PERSUADE_FAIL",
          "type": "npc_line",
          "speakerId": "BAY_SUPERVISOR",
          "text": "Clearing you doesn\u0019t change anything here. (pause)\nRun the sequence. (pause)\nKeep the record clean. (pause)\nThen the door behaves.",
          "next": "N_REDIRECT_HUB"
        },
        {
          "id": "N_REDIRECT_HUB",
          "type": "redirect",
          "target": "N_HUB"
        },
        {
          "id": "N_END_BACK",
          "type": "end"
        }
      ]
    }
  ]
}