{
  "dialogueGraphs": [
    {
      "id": "DG_SCN018_CALL_LEGAL",
      "sceneId": "SCN-018",
      "startNodeId": "N001_INTRO",
      "nodes": [
        {
          "id": "N001_INTRO",
          "type": "npc_line",
          "speakerId": "NARRATOR",
          "text": "The wall phone list is laminated, updated, and slightly curled at the corners (pause) like it\u2019s been worried by too many careful hands. (pause) \u201cOLEA \u2014 LEGAL (Work Orders / Waivers)\u201d is circled in fading pen.",
          "next": "N002_START_CHOICE"
        },
        {
          "id": "N002_START_CHOICE",
          "type": "player_choice",
          "speakerId": "PLAYER",
          "choices": [
            {
              "id": "C_USE_CALL",
              "text": "use: Call OLEA Legal.",
              "next": "N003_DIALTONE"
            },
            {
              "id": "C_LEAVE",
              "text": "leave: Don\u2019t call.",
              "next": "N900_END_NO_OUTCOME"
            }
          ]
        },
        {
          "id": "N003_DIALTONE",
          "type": "npc_line",
          "speakerId": "NARRATOR",
          "text": "The handset is heavier than it needs to be. (pause) The dial tone arrives with the patience of something that expects to be blamed later.",
          "next": "N004_PICKUP"
        },
        {
          "id": "N004_PICKUP",
          "type": "npc_line",
          "speakerId": "NARRATOR",
          "text": "After three rings, someone answers without saying hello.",
          "next": "N005_LEGAL_GREETING"
        },
        {
          "id": "N005_LEGAL_GREETING",
          "type": "npc_line",
          "speakerId": "OLEA_LEGAL",
          "text": "Office of Legacy Energy Assets, Legal. (pause) Recorded line. (pause) Name and assignment.",
          "next": "N006_PLAYER_ID"
        },
        {
          "id": "N006_PLAYER_ID",
          "type": "npc_line",
          "speakerId": "PLAYER",
          "text": "Field Systems Specialist. SPINDLE closure.",
          "next": "N007_LEGAL_SCOPE"
        },
        {
          "id": "N007_LEGAL_SCOPE",
          "type": "npc_line",
          "speakerId": "OLEA_LEGAL",
          "text": "\u201cClosure activities.\u201d (pause) Okay. (pause) I\u2019ll get the paper moving. (pause) I\u2019m not signing anything that looks like fieldwork. (pause) And don\u2019t say \u201cauthorize\u201d on my line.",
          "next": "N010_MAIN_MENU"
        },
        {
          "id": "N010_MAIN_MENU",
          "type": "player_choice",
          "speakerId": "PLAYER",
          "choices": [
            {
              "id": "C_TALK_AUTH",
              "text": "talk: I need authorization to enter and proceed.",
              "next": "N020_AUTH_REBUKE"
            },
            {
              "id": "C_ASK_WORKORDER",
              "text": "ask: I need a Work Order.",
              "next": "N040_WORKORDER_DIRECT"
            },
            {
              "id": "C_ASK_WRITING",
              "text": "ask: What can you put in writing?",
              "next": "N030_WRITING"
            },
            {
              "id": "C_LEAVE_HANGUP",
              "text": "leave: Hang up.",
              "next": "N900_END_NO_OUTCOME"
            }
          ]
        },
        {
          "id": "N020_AUTH_REBUKE",
          "type": "npc_line",
          "speakerId": "OLEA_LEGAL",
          "text": "I can\u2019t give you \u201cauthorization to enter.\u201d (pause) That makes it sound like we checked conditions. (pause) We haven\u2019t. (pause) What I can sign is a Work Order\u2014 (pause) tight scope: one asset and closure documentation. (pause) That\u2019s what I\u2019m allowed to sign.",
          "next": "N021_REPHRASE_MENU"
        },
        {
          "id": "N021_REPHRASE_MENU",
          "type": "player_choice",
          "speakerId": "PLAYER",
          "choices": [
            {
              "id": "C_ASK_ISSUE_WO",
              "text": "ask: Then issue the Work Order.",
              "next": "N050_NEED_ASSET_ID"
            },
            {
              "id": "C_ASK_ALLOWED_WORDS",
              "text": "ask: So what am I allowed to say I\u2019m doing?",
              "next": "N022_ALLOWED_SAY"
            },
            {
              "id": "C_TALK_COVERAGE",
              "text": "talk: I\u2019m standing at the site. I need coverage.",
              "next": "N023_COVERAGE"
            },
            {
              "id": "C_LOOPBACK_MAIN",
              "text": "ask: Back up. Start over.",
              "next": "N011_REDIRECT_MAIN"
            },
            {
              "id": "C_LEAVE_ENDCALL",
              "text": "leave: End call.",
              "next": "N900_END_NO_OUTCOME"
            }
          ]
        },
        {
          "id": "N011_REDIRECT_MAIN",
          "type": "redirect",
          "target": "N010_MAIN_MENU"
        },
        {
          "id": "N022_ALLOWED_SAY",
          "type": "npc_line",
          "speakerId": "OLEA_LEGAL",
          "text": "Say you\u2019re \u201con site for closure documentation.\u201d (pause)\nKeep \u201cinvestigating\u201d out. (pause)\nSame with \u201cevaluating anomalous conditions.\u201d (pause)\nSame with \u201cconfirming safety.\u201d (pause)\nDon\u2019t put those words in your mouth. (pause)\nStick to the checklist. (pause)\nFunding deadline\u2019s on us. (pause)\nThat\u2019s it.",
          "next": "N022B_ALLOWED_MENU"
        },
        {
          "id": "N022B_ALLOWED_MENU",
          "type": "player_choice",
          "speakerId": "PLAYER",
          "choices": [
            {
              "id": "C_ALLOWED_ISSUE",
              "text": "ask: Then issue the Work Order.",
              "next": "N050_NEED_ASSET_ID"
            },
            {
              "id": "C_ALLOWED_LOOPBACK",
              "text": "ask: Back to the main question.",
              "next": "N011_REDIRECT_MAIN"
            },
            {
              "id": "C_ALLOWED_LEAVE",
              "text": "leave: End call.",
              "next": "N900_END_NO_OUTCOME"
            }
          ]
        },
        {
          "id": "N023_COVERAGE",
          "type": "npc_line",
          "speakerId": "OLEA_LEGAL",
          "text": "I can cover one narrow task (pause) on one specific asset. (pause) I\u2019m not giving you a blanket line. (pause) It can't read like we saw it coming. (pause) You want coverage\u2014 (pause) keep it boring. (pause) Keep it specific.",
          "next": "N021_REPHRASE_MENU"
        },
        {
          "id": "N030_WRITING",
          "type": "npc_line",
          "speakerId": "OLEA_LEGAL",
          "text": "A Work Order. (pause) A waiver. (pause) A memo: the call happened. (pause) I\u2019m not writing anything (pause) that says we predicted outcomes or endorsed conditions (pause) or \u201cauthorized entry.\u201d (pause) That turns a building into a promise.",
          "next": "N031_WRITING_MENU"
        },
        {
          "id": "N031_WRITING_MENU",
          "type": "player_choice",
          "speakerId": "PLAYER",
          "choices": [
            {
              "id": "C_WRITING_WORKORDER",
              "text": "ask: I need a Work Order.",
              "next": "N040_WORKORDER_DIRECT"
            },
            {
              "id": "C_WRITING_NOAUTH",
              "text": "talk: Fine. Authorization isn\u2019t the word.",
              "next": "N020_AUTH_REBUKE"
            },
            {
              "id": "C_WRITING_LEAVE",
              "text": "leave: End call.",
              "next": "N900_END_NO_OUTCOME"
            }
          ]
        },
        {
          "id": "N040_WORKORDER_DIRECT",
          "type": "npc_line",
          "speakerId": "OLEA_LEGAL",
          "text": "Alright. Work Order I can do. (pause) It has to hang off an asset. (pause) Give me the asset ID.",
          "next": "N060_ASSET_MENU"
        },
        {
          "id": "N050_NEED_ASSET_ID",
          "type": "npc_line",
          "speakerId": "OLEA_LEGAL",
          "text": "I can\u2014once I have the asset identifier. (pause) The one in the register. (pause) Save me the nickname, the acronym. (pause) People freestyle this part. (pause) Then we spend six months (pause) calling it a \u201cclerical error.\u201d",
          "next": "N060_ASSET_MENU"
        },
        {
          "id": "N060_ASSET_MENU",
          "type": "player_choice",
          "speakerId": "PLAYER",
          "choices": [
            {
              "id": "C_GIVE_SP01",
              "text": "give: Asset ID is SP-01.",
              "conditions": [
                {
                  "key": "clues.assetId_SP01",
                  "op": "==",
                  "value": true
                }
              ],
              "next": "N070_SP01_CONFIRM"
            },
            {
              "id": "C_TALK_NO_ID",
              "text": "talk: I don\u2019t have the asset ID in front of me.",
              "next": "N080_NO_ID"
            },
            {
              "id": "C_LOOK_REGISTER",
              "text": "look: What does the register call it?",
              "next": "N090_LOOKUP_REFUSAL"
            },
            {
              "id": "C_PERSUADE_PROVISIONAL",
              "text": "persuade: Issue it provisionally; I\u2019ll confirm the ID after.",
              "checks": [
                {
                  "type": "skill",
                  "skill": "PROCEDURE",
                  "dc": 12
                }
              ],
              "onPassNext": "N100_PERSUADE_PASS",
              "onFailNext": "N101_PERSUADE_FAIL"
            },
            {
              "id": "C_LOOPBACK_MAIN_FROM_ASSET",
              "text": "ask: Back to the main menu.",
              "next": "N011_REDIRECT_MAIN"
            },
            {
              "id": "C_LEAVE_ASSET",
              "text": "leave: End call.",
              "next": "N900_END_NO_OUTCOME"
            }
          ]
        },
        {
          "id": "N070_SP01_CONFIRM",
          "type": "npc_line",
          "speakerId": "OLEA_LEGAL",
          "text": "SP-zero-one. Good. (pause)\nI\u2019m issuing the Work Order now. (pause)\nClosure-support only\u2014verification and documentation. (pause)\nStandard retirement checklist. (pause)\nNo deviation. (pause)\nDon\u2019t write anything that sounds like \u201ctesting.\u201d (pause)\nI\u2019ll fax it to the facility\u2019s posted number.",
          "next": "N071_CLOSE_MENU"
        },
        {
          "id": "N071_CLOSE_MENU",
          "type": "player_choice",
          "speakerId": "PLAYER",
          "choices": [
            {
              "id": "C_ASK_REFNUM",
              "text": "ask: Give me the reference number.",
              "next": "N072_REFNUM"
            },
            {
              "id": "C_TALK_SEND",
              "text": "talk: No. Just send it.",
              "next": "N073_SEND"
            }
          ]
        },
        {
          "id": "N072_REFNUM",
          "type": "npc_line",
          "speakerId": "OLEA_LEGAL",
          "text": "Reference number\u2019s WO-RET-SP01. (pause) Write that. (pause) Leave \u201cauthorized\u201d out. (pause) Write: \u201cWork Order issued for SP-01 closure documentation.\u201d",
          "next": "N800_END_WITH_ID"
        },
        {
          "id": "N073_SEND",
          "type": "npc_line",
          "speakerId": "OLEA_LEGAL",
          "text": "I\u2019m sending it. (pause)\nDon\u2019t call it \u201cauthorization.\u201d (pause)\nCall it: \u201cWork Order issued for SP-01 (pause) closure documentation.\u201d (pause)\nBye.",
          "next": "N800_END_WITH_ID"
        },
        {
          "id": "N080_NO_ID",
          "type": "npc_line",
          "speakerId": "OLEA_LEGAL",
          "text": "Then I can\u2019t issue anything. (pause)\nWrong asset on the Work Order (pause)\nturns \u201ccoverage\u201d into a discrepancy. (pause)\nAnd discrepancies grow legs. (pause)\nFind the plaque. (pause)\nFind the posted register. (pause)\nFind the asset tag. (pause)\nWhatever passes for ID out there. (pause)\nCall me back.",
          "next": "N810_END_WITHOUT_ID"
        },
        {
          "id": "N090_LOOKUP_REFUSAL",
          "type": "npc_line",
          "speakerId": "OLEA_LEGAL",
          "text": "I\u2019m not your registry service. (pause)\nYeah there\u2019s an Asset Register. (pause)\nNo, I\u2019m not reading it on record. (pause)\nI\u2019m not buying a later fight over knowledge\u2014 (pause)\nor when. (pause)\nYou\u2019re onsite. Use the onsite label. (pause)\nCall me with the plaque text.",
          "next": "N810_END_WITHOUT_ID"
        },
        {
          "id": "N100_PERSUADE_PASS",
          "type": "npc_line",
          "speakerId": "OLEA_LEGAL",
          "text": "Cute. (pause) No. (pause)\n\u201cProvisional\u201d doesn\u2019t land\u2014 (pause)\nnowhere to file it. (pause)\nNeed something to say now, use this: (pause)\n\u201cI am conducting site preservation and closure documentation. (pause)\nPending issuance of a Work Order.\u201d (pause)\nBring me the asset ID. (pause)\nI\u2019ll issue the actual instrument.",
          "next": "N810_END_WITHOUT_ID"
        },
        {
          "id": "N101_PERSUADE_FAIL",
          "type": "npc_line",
          "speakerId": "OLEA_LEGAL",
          "text": "No. (pause) I can give you wording. (pause) I can\u2019t issue instruments (pause) without an identifier. (pause) Call back with the ID. (pause) The system only behaves with specifics. (pause) Rush jobs get ugly.",
          "next": "N810_END_WITHOUT_ID"
        },
        {
          "id": "N800_END_WITH_ID",
          "type": "end",
          "outcomeId": "call_legal_with_asset_id",
          "effects": [
            {
              "key": "paperwork.workOrderRequested",
              "action": "set",
              "value": true
            },
            {
              "key": "paperwork.notes",
              "action": "add",
              "value": "Work Order issued by Legal for SP-01; routed to posted facility fax."
            }
          ]
        },
        {
          "id": "N810_END_WITHOUT_ID",
          "type": "end",
          "outcomeId": "call_legal_without_asset_id",
          "effects": [
            {
              "key": "paperwork.workOrderRequested",
              "action": "set",
              "value": false
            },
            {
              "key": "paperwork.notes",
              "action": "add",
              "value": "Legal: needs asset ID to issue Work Order. Refused \u2018authorization\u2019 language."
            }
          ]
        },
        {
          "id": "N900_END_NO_OUTCOME",
          "type": "end"
        }
      ]
    }
  ]
}