{
  "changes": [
    {
      "action": "add",
      "createScene": {
        "dialogueGraphs": [
          {
            "id": "DG_INSTRUMENT_CONDUIT_BOX",
            "nodes": [
              {
                "id": "N_CONDUIT_DESC",
                "next": "N_CONDUIT_MENU",
                "speakerId": "NARRATOR",
                "text": "A metal conduit box sits by the fence with a padlock that has been replaced more recently than the bolts holding the box to the post.\nA label reads: INSTRUMENTATION \u2014 DO NOT DE-ENERGIZE, and someone has underlined \u201cDO\u201d twice.",
                "type": "npc_line"
              },
              {
                "choices": [
                  {
                    "id": "C_END",
                    "next": "END",
                    "text": "leave Back."
                  }
                ],
                "id": "N_CONDUIT_MENU",
                "speakerId": "PLAYER",
                "type": "player_choice"
              }
            ],
            "sceneId": "SCN-076",
            "startNodeId": "N_CONDUIT_DESC"
          }
        ]
      },
      "op": "create_scene"
    }
  ],
  "sceneId": "SCN-076"
}